ai_flow/__init__.py
ai_flow/__main__.py
ai_flow/alembic.ini
ai_flow/settings.py
ai_flow/version.py
ai_flow/blob_manager/__init__.py
ai_flow/blob_manager/blob_manager_interface.py
ai_flow/blob_manager/impl/__init__.py
ai_flow/blob_manager/impl/hdfs_blob_manager.py
ai_flow/blob_manager/impl/local_blob_manager.py
ai_flow/blob_manager/impl/oss_blob_manager.py
ai_flow/blob_manager/impl/s3_blob_manager.py
ai_flow/cli/__init__.py
ai_flow/cli/cli_parser.py
ai_flow/cli/simple_table.py
ai_flow/cli/commands/__init__.py
ai_flow/cli/commands/config_command.py
ai_flow/cli/commands/db_command.py
ai_flow/cli/commands/namespace_command.py
ai_flow/cli/commands/server_command.py
ai_flow/cli/commands/task_execution_command.py
ai_flow/cli/commands/task_manager_command.py
ai_flow/cli/commands/version_command.py
ai_flow/cli/commands/workflow_command.py
ai_flow/cli/commands/workflow_execution_command.py
ai_flow/cli/commands/workflow_schedule_command.py
ai_flow/cli/commands/workflow_trigger_command.py
ai_flow/common/__init__.py
ai_flow/common/entity.py
ai_flow/common/env.py
ai_flow/common/properties.py
ai_flow/common/result.py
ai_flow/common/configuration/__init__.py
ai_flow/common/configuration/config_constants.py
ai_flow/common/configuration/configuration.py
ai_flow/common/configuration/helpers.py
ai_flow/common/configuration/config_templates/__init__.py
ai_flow/common/configuration/config_templates/aiflow_client.yaml
ai_flow/common/configuration/config_templates/aiflow_server.yaml
ai_flow/common/exception/__init__.py
ai_flow/common/exception/exceptions.py
ai_flow/common/util/__init__.py
ai_flow/common/util/cli_utils.py
ai_flow/common/util/json_utils.py
ai_flow/common/util/kubernetes_util.py
ai_flow/common/util/local_registry.py
ai_flow/common/util/mock_context.py
ai_flow/common/util/module_utils.py
ai_flow/common/util/net_utils.py
ai_flow/common/util/process_utils.py
ai_flow/common/util/string_utils.py
ai_flow/common/util/thread_utils.py
ai_flow/common/util/time_utils.py
ai_flow_nightly-2023.12.31.dist-info/LICENSE
ai_flow_nightly-2023.12.31.dist-info/METADATA
ai_flow_nightly-2023.12.31.dist-info/NOTICE
ai_flow_nightly-2023.12.31.dist-info/WHEEL
ai_flow_nightly-2023.12.31.dist-info/entry_points.txt
ai_flow_nightly-2023.12.31.dist-info/top_level.txt
ai_flow_nightly-2023.12.31.dist-info/RECORD
